CHANGES.rst
MANIFEST.in
README.rst
setup.py
xuproc
src/xupdate_processor/__init__.py
src/xupdate_processor/content_handler.py
src/xupdate_processor/xuproc.py
src/xupdate_processor.egg-info/PKG-INFO
src/xupdate_processor.egg-info/SOURCES.txt
src/xupdate_processor.egg-info/dependency_links.txt
src/xupdate_processor.egg-info/not-zip-safe
src/xupdate_processor.egg-info/requires.txt
src/xupdate_processor.egg-info/top_level.txt
src/xupdate_processor/tests/__init__.py
src/xupdate_processor/tests/test_xupdate_processor.py