Metadata-Version: 1.1
Name: xupdate-processor
Version: 0.5
Summary: XUpdate Processor
Home-page: https://lab.nexedi.com/nexedi/xupdate_processor
Author: Nicolas DELABY
Author-email: nicolas@nexedi.com
License: GPL
Platform: UNKNOWN
Classifier: License :: OSI Approved :: GNU General Public License (GPL)
Classifier: Operating System :: OS Independent
Classifier: Topic :: Text Processing :: Markup :: XML
Classifier: Topic :: Utilities
